fbc/__init__.py
fbc/__main__.py
fbc/fbc.py
fbc/format.py
fbc/main.py
fbc/targets.py
fbc/testers/__init__.py
fbc/testers/basic_domain.py
fbc/testers/generic.py
fbc/testers/quic.py
fbc/utils/__init__.py
fbc/utils/http3.py
fast_blockcheck-1.1.dist-info/LICENCE
fast_blockcheck-1.1.dist-info/METADATA
fast_blockcheck-1.1.dist-info/WHEEL
fast_blockcheck-1.1.dist-info/entry_points.txt
fast_blockcheck-1.1.dist-info/top_level.txt
fast_blockcheck-1.1.dist-info/RECORD
