Metadata-Version: 2.1
Name: fast-blockcheck
Version: 1.1
Summary: Track internet blocking over time
Author: usiqwerty
Project-URL: Homepage, https://github.com/usiqwerty/fast-blockcheck
Project-URL: Issues, https://github.com/usiqwerty/fast-blockcheck/issues
Classifier: Programming Language :: Python :: 3
Classifier: License :: OSI Approved :: GNU Affero General Public License v3
Classifier: Operating System :: OS Independent
Classifier: Natural Language :: English
Classifier: Environment :: Console
Classifier: Intended Audience :: End Users/Desktop
Classifier: Intended Audience :: Developers
Classifier: Intended Audience :: System Administrators
Classifier: Intended Audience :: Science/Research
Classifier: Topic :: Utilities
Classifier: Typing :: Typed
Requires-Python: >=3.8
License-File: LICENCE
Requires-Dist: requests
